ZohoSolutionsSuite/__init__.py
ZohoSolutionsSuite/auth.py
ZohoSolutionsSuite/books/__init__.py
ZohoSolutionsSuite/creator/__init__.py
ZohoSolutionsSuite/crm/__init__.py
ZohoSolutionsSuite/crm/records.py
ZohoSolutionsSuite/desk/__init__.py
ZohoSolutionsSuite/inventory/__init__.py
ZohoSolutionsSuite/projects/__init__.py
ZohoSolutionsSuite-0.1.2.dist-info/METADATA
ZohoSolutionsSuite-0.1.2.dist-info/WHEEL
ZohoSolutionsSuite-0.1.2.dist-info/top_level.txt
ZohoSolutionsSuite-0.1.2.dist-info/RECORD
