Metadata-Version: 2.1
Name: ZohoSolutionsSuite
Version: 0.1.2
Summary: Wrapper for Zoho API operations; migration, automations,  etc.
Home-page: UNKNOWN
Author: Dylan Garrett
Author-email: dylan.g@zohocorp.com
License: UNKNOWN
Keywords: zoho,crm,api,tools,migration
Platform: UNKNOWN
